pypldl/__init__.py
pypldl/__main__.py
pypldl/cli.py
pypldl/core.py
pypldl/gui.py
pypldl/plugins/__init__.py
pypldl/plugins/batoto.py
pypldl/plugins/kissmanga.py
pypldl/plugins/manga.py
pypldl/plugins/mangafox.py
pypldl/plugins/mangaframework.py
pypldl/plugins/mangahere.py
pypldl/plugins/readcomiconline.py
pypldl-2.1.1.dist-info/METADATA
pypldl-2.1.1.dist-info/WHEEL
pypldl-2.1.1.dist-info/entry_points.txt
pypldl-2.1.1.dist-info/top_level.txt
pypldl-2.1.1.dist-info/RECORD
