Metadata-Version: 2.1
Name: pypldl
Version: 2.1.1
Summary: A crawler with parallel downloading
Home-page: UNKNOWN
Author: Benoît Ryder
Author-email: benoit@ryder.fr
License: MIT
Platform: UNKNOWN
Classifier: License :: OSI Approved :: MIT License
Classifier: Programming Language :: Python :: 3.6
Classifier: Programming Language :: Python :: 3.7
Requires-Dist: beautifulsoup4
Requires-Dist: urllib3
Requires-Dist: html5lib
